oru2xds/__init__.py
oru2xds/__version__.py
oru2xds/config.py
oru2xds/hl7_cda.py
oru2xds/hl7_v2x_receiver.py
oru2xds/ihe_xds.py
oru2xds/oru2xds.py
oru2xds/soap.py
oru2xds/examples/sample-ADT-A01.hl7
oru2xds/examples/sample3-ORU-R01.hl7
oru2xds-2.0.25.dist-info/LICENSE.md
oru2xds-2.0.25.dist-info/METADATA
oru2xds-2.0.25.dist-info/WHEEL
oru2xds-2.0.25.dist-info/top_level.txt
oru2xds-2.0.25.dist-info/RECORD
