Metadata-Version: 2.1
Name: oru2xds
Version: 2.0.25
Summary: Receive HL7 messages and send them to an XDS.b repository
Author-email: Antonio Martins <digiplan.pt@gmail.com>
License: GPL-3.0-or-later
Classifier: Development Status :: 4 - Beta
Classifier: Intended Audience :: Developers
Classifier: License :: OSI Approved :: MIT License
Classifier: Operating System :: OS Independent
Classifier: Programming Language :: Python :: 3
Requires-Python: >=3.7
License-File: LICENSE.md
Requires-Dist: aiorun ==2022.4.1
Requires-Dist: hl7 ==0.4.5
Requires-Dist: lxml ==4.8.0
Requires-Dist: requests ==2.25.1
Requires-Dist: requests-toolbelt ==0.9.1
Requires-Dist: striprtf ==0.0.20
Requires-Dist: sympy ==1.10.1
Requires-Dist: urllib3 ==1.26.5
